odoo/addons/sale_order_change_analytic_account/README.rst
odoo/addons/sale_order_change_analytic_account/__init__.py
odoo/addons/sale_order_change_analytic_account/__manifest__.py
odoo/addons/sale_order_change_analytic_account/i18n/es.po
odoo/addons/sale_order_change_analytic_account/i18n/it.po
odoo/addons/sale_order_change_analytic_account/i18n/sale_order_change_analytic_account.pot
odoo/addons/sale_order_change_analytic_account/models/__init__.py
odoo/addons/sale_order_change_analytic_account/models/sale_order.py
odoo/addons/sale_order_change_analytic_account/readme/CONTRIBUTORS.rst
odoo/addons/sale_order_change_analytic_account/readme/DESCRIPTION.rst
odoo/addons/sale_order_change_analytic_account/security/sale_order_change_analytic.xml
odoo/addons/sale_order_change_analytic_account/static/description/icon.png
odoo/addons/sale_order_change_analytic_account/static/description/index.html
odoo/addons/sale_order_change_analytic_account/tests/__init__.py
odoo/addons/sale_order_change_analytic_account/tests/test_sale_order_change_analytic.py
odoo/addons/sale_order_change_analytic_account/views/sale_order.xml
odoo/addons/sale_order_change_analytic_account/wizards/__init__.py
odoo/addons/sale_order_change_analytic_account/wizards/sale_order_change_analytic.py
odoo/addons/sale_order_change_analytic_account/wizards/sale_order_change_analytic.xml
odoo14_addon_sale_order_change_analytic_account-14.0.1.0.1.dev7.dist-info/METADATA
odoo14_addon_sale_order_change_analytic_account-14.0.1.0.1.dev7.dist-info/WHEEL
odoo14_addon_sale_order_change_analytic_account-14.0.1.0.1.dev7.dist-info/top_level.txt
odoo14_addon_sale_order_change_analytic_account-14.0.1.0.1.dev7.dist-info/RECORD
